contract_bootloader/__init__.py
contract_bootloader/contract.cairo
contract_bootloader/contract_bootloader.cairo
contract_bootloader/contract_dry_run.cairo
contract_bootloader/dryrun_syscall_handler.py
contract_bootloader/execute_entry_point.cairo
contract_bootloader/execute_syscalls.cairo
contract_bootloader/syscall_handler.py
contract_bootloader/syscall_handler_base.py
contract_bootloader/contract_class/__init__.py
contract_bootloader/contract_class/compiled_class.cairo
contract_bootloader/contract_class/compiled_class_hash_utils.py
contract_bootloader/contract_class/contract_class.cairo
contract_bootloader/contract_class/contract_class.py
contract_bootloader/dryrun_syscall_memorizer_handler/__init__.py
contract_bootloader/dryrun_syscall_memorizer_handler/evm/__init__.py
contract_bootloader/dryrun_syscall_memorizer_handler/evm/account_handler.py
contract_bootloader/dryrun_syscall_memorizer_handler/evm/block_receipt_handler.py
contract_bootloader/dryrun_syscall_memorizer_handler/evm/block_tx_handler.py
contract_bootloader/dryrun_syscall_memorizer_handler/evm/header_handler.py
contract_bootloader/dryrun_syscall_memorizer_handler/evm/storage_handler.py
contract_bootloader/dryrun_syscall_memorizer_handler/starknet/__init__.py
contract_bootloader/dryrun_syscall_memorizer_handler/starknet/header_handler.py
contract_bootloader/dryrun_syscall_memorizer_handler/starknet/storage_handler.py
contract_bootloader/memorizer/__init__.py
contract_bootloader/memorizer/evm/__init__.py
contract_bootloader/memorizer/evm/account.py
contract_bootloader/memorizer/evm/block_receipt.py
contract_bootloader/memorizer/evm/block_tx.py
contract_bootloader/memorizer/evm/header.py
contract_bootloader/memorizer/evm/memorizer.py
contract_bootloader/memorizer/evm/storage.py
contract_bootloader/memorizer/starknet/__init__.py
contract_bootloader/memorizer/starknet/header.py
contract_bootloader/memorizer/starknet/memorizer.py
contract_bootloader/memorizer/starknet/storage.py
hdp_cairo_dev-0.0.20.dist-info/LICENSE
hdp_cairo_dev-0.0.20.dist-info/METADATA
hdp_cairo_dev-0.0.20.dist-info/WHEEL
hdp_cairo_dev-0.0.20.dist-info/top_level.txt
hdp_cairo_dev-0.0.20.dist-info/RECORD
