Metadata-Version: 2.1
Name: hdp-cairo-dev
Version: 0.0.20
License-File: LICENSE
Requires-Dist: aiofiles==23.2.1
Requires-Dist: typeguard==2.13.3
Requires-Dist: protobuf==3.20.3
Requires-Dist: inquirer
Requires-Dist: python-dotenv==1.0.1
Requires-Dist: pysha3
Requires-Dist: web3==7.4.0
Requires-Dist: black
Requires-Dist: poseidon-py
Requires-Dist: trie==3.0.1
Requires-Dist: sympy==1.12.1
